gtagoraapp/__init__.py
gtagoraapp/__main__.py
gtagoraapp/agoraapp.py
gtagoraapp/details/__init__.py
gtagoraapp/details/app.py
gtagoraapp/details/settings.py
gtagoraapp/details/ws.py
gtagora_app-2.9.0.dist-info/LICENSE
gtagora_app-2.9.0.dist-info/METADATA
gtagora_app-2.9.0.dist-info/WHEEL
gtagora_app-2.9.0.dist-info/entry_points.txt
gtagora_app-2.9.0.dist-info/top_level.txt
gtagora_app-2.9.0.dist-info/RECORD
