Metadata-Version: 2.1
Name: gtagora-app
Version: 2.9.0
Summary: Python version of the Agora app
Home-page: https://github.com/gyrotools/gtagora-app-py
Author: Martin Bührer
Author-email: info@gyrotools.com
License: UNKNOWN
Platform: UNKNOWN
Classifier: Programming Language :: Python :: 3
Classifier: License :: OSI Approved :: MIT License
Classifier: Operating System :: OS Independent
Requires-Python: >=3.6.0
Requires-Dist: websockets
Requires-Dist: gtagora-connector
